{
  "type": "object",
  "properties": {
    "task_name": {
      "type": "string"
    },
    "description": {
      "type": "string"
    },
    "owner": {
      "type": "string",
      "enum": [
        "Antonio",
        "Anthony"
      ]
    },
    "frequency": {
      "type": "string",
      "enum": [
        "daily",
        "weekly",
        "monthly",
        "one_time"
      ]
    },
    "status": {
      "type": "string",
      "enum": [
        "pending",
        "in_progress",
        "completed"
      ]
    },
    "due_date": {
      "type": "string"
    },
    "priority": {
      "type": "string",
      "enum": [
        "high",
        "medium",
        "low"
      ]
    },
    "notes": {
      "type": "string"
    },
    "category": {
      "type": "string"
    }
  },
  "required": [],
  "name": "OpsTracker"
}